agrifrika_shared/__init__.py
agrifrika_shared/identity.py
agrifrika_shared/notification.py
agrifrika_shared/aws/__init__.py
agrifrika_shared/aws/clients.py
agrifrika_shared/aws/cognito_client.py
agrifrika_shared/aws/dynamo_client.py
agrifrika_shared/aws/s3_client.py
agrifrika_shared/config/__init__.py
agrifrika_shared/events/__init__.py
agrifrika_shared/events/domain_events.py
agrifrika_shared/events/emitter.py
agrifrika_shared/handlers/__init__.py
agrifrika_shared/handlers/base_handler.py
agrifrika_shared/local_testing/__init__.py
agrifrika_shared/local_testing/event_converter.py
agrifrika_shared/local_testing/local_dev_helper.py
agrifrika_shared/local_testing/mock_context.py
agrifrika_shared/models/__init__.py
agrifrika_shared/models/base.py
agrifrika_shared/models/common.py
agrifrika_shared/utils/__init__.py
agrifrika_shared/utils/exceptions.py
agrifrika_shared/utils/logger.py
agrifrika_shared/utils/request_parser.py
agrifrika_shared/utils/response_builder.py
agrifrika_shared/utils/validators.py
tests/__init__.py
tests/conftest.py
tests/integration/__init__.py
tests/integration/test_aws_integration.py
tests/unit/__init__.py
tests/unit/test_aws_clients.py
tests/unit/test_base_models.py
tests/unit/test_common_models.py
tests/unit/test_exceptions.py
tests/unit/test_local_testing.py
tests/unit/test_logger.py
tests/unit/test_request_parser.py
tests/unit/test_response_builder.py
tests/unit/test_validators.py
agrifrika_shared-0.3.13.dist-info/METADATA
agrifrika_shared-0.3.13.dist-info/WHEEL
agrifrika_shared-0.3.13.dist-info/top_level.txt
agrifrika_shared-0.3.13.dist-info/RECORD
