Metadata-Version: 2.4
Name: agrifrika-shared
Version: 0.3.13
Summary: Shared utilities and models for Agrifrika microservices
Home-page: https://github.com/agrifrika/agrifrika-backend
Author: Agrifrika Team
Author-email: Agrifrika Team <tech@agrifrika.com>
License: MIT
Requires-Python: >=3.9
Requires-Dist: pydantic>=2.0.0
Requires-Dist: python-dateutil>=2.8.0
Provides-Extra: dev
Requires-Dist: pytest>=7.0.0; extra == "dev"
Requires-Dist: pytest-cov>=4.0.0; extra == "dev"
Requires-Dist: pytest-mock>=3.10.0; extra == "dev"
Requires-Dist: black>=23.0.0; extra == "dev"
Requires-Dist: isort>=5.12.0; extra == "dev"
Requires-Dist: mypy>=1.0.0; extra == "dev"
Requires-Dist: ruff>=0.1.0; extra == "dev"
Requires-Dist: boto3>=1.26.0; extra == "dev"
Requires-Dist: moto>=4.0.0; extra == "dev"
Dynamic: author
Dynamic: home-page
Dynamic: requires-python
